fount_eda/__init__.py
fount_eda/edaclass.build/.gitignore
fount_eda/edaclass.build/.sconsign-312.dblite
fount_eda/edaclass.build/@link_input.txt
fount_eda/edaclass.build/__bytecode.const
fount_eda/edaclass.build/__constants.bin
fount_eda/edaclass.build/__constants.c
fount_eda/edaclass.build/__constants.const
fount_eda/edaclass.build/__constants.h
fount_eda/edaclass.build/__constants.os
fount_eda/edaclass.build/__constants.txt
fount_eda/edaclass.build/__helpers.c
fount_eda/edaclass.build/__helpers.h
fount_eda/edaclass.build/__helpers.os
fount_eda/edaclass.build/__loader.c
fount_eda/edaclass.build/__loader.os
fount_eda/edaclass.build/build_definitions.h
fount_eda/edaclass.build/ccache-24897.txt
fount_eda/edaclass.build/module.edaclass.c
fount_eda/edaclass.build/module.edaclass.const
fount_eda/edaclass.build/module.edaclass.os
fount_eda/edaclass.build/scons-debug.py
fount_eda/edaclass.build/scons-debug.sh
fount_eda/edaclass.build/scons-report.txt
fount_eda/edaclass.build/static_src/CompiledFunctionType.c
fount_eda/edaclass.build/static_src/CompiledFunctionType.os
fount_eda/edaclass.cpython-312-darwin.so
fount_eda/edaclass.pyi
fount_eda-0.1.4.4.dist-info/WHEEL
fount_eda-0.1.4.4.dist-info/METADATA
fount_eda-0.1.4.4.dist-info/RECORD
