Metadata-Version: 2.4
Name: fount-eda
Version: 0.1.4.4
Summary: EDA tool for Fount
Author: Bibek Sahu
Author-email: Bibek Sahu <bibek@datapoem.com>
License-Expression: MIT
Requires-Dist: pandas>=2.3.2
Requires-Dist: scikit-learn>=1.7.2
Requires-Dist: statsmodels>=0.14.5
Requires-Python: >=3.12
